Metadata-Version: 1.0
Name: ckpl
Version: 0.3.1
Summary: Ckoirama Pipeline
Home-page: https://github.com/ckoirama/ckpl
Author: Ckoirama team
Author-email: rodrigo.gonzalez@uamail.cl
License: MIT
Platform: UNKNOWN
